{
  "projects": [
    {
      "id": 1,
      "title": "Smock",
      "description": "A full-fledged E-commerce clothing store",
      "image": [
        "/images/smock 1.png",
        "/images/smock 2.png",
        "/images/smock 3.png",
        "/images/smock 4.png",
        "/images/smock 5.png"
      ],
      "slug": "smock",
      "deploy": "",
      "frontend": "https://github.com/rahul12km/smock-E-commerce-website-frontend-",
      "backend": "https://github.com/rahul12km/smock-E-commerce-website-backend-",
      "techUsed": "MERN Stack | Redux | Redux Toolkit | Jwt | RazorPay | Firebase | tailwind "
    },
    {
      "id": 2,
      "title": "Movflix",
      "description": "A comprehensive movie database platform, offering users a rich repository of film information and ratings",
      "image": [
        "/images/mov ss1.png",
        "/images/mov ss2.png",
        "/images/mov ss3.png",
        "/images/mov ss4.png"
      ],
      "slug": "movflix",
      "deploy": "https://movies-app-beta-mauve.vercel.app/",
      "frontend": "https://github.com/rahul12km/Movies-app",
      "backend": "",
      "techUsed": "ReactJS | RestApi | SaaS | React-Youtube | InfiniteScroll "
    },
    {
      "id": 3,
      "title": "Cryptoverse",
      "description": "A Cryptocurrency data aggregator and analytics platform",
      "image": [
        "/images/crypto ss1.png",
        "/images/crypto ss2.png",
        "/images/crypto ss3.png",
        "/images/crypto ss4.png"
      ],
      "slug": "cryptoverse",
      "deploy": "https://cryptoverse-three-beta.vercel.app/",
      "frontend": "https://github.com/rahul12km/cryptoverse",
      "backend": "",
      "techUsed": "RectJs | RestApi | ChartJS | Vanila CSS"
    },
    {
      "id": 4,
      "title": "Snappy",
      "description": "A chat app  with customizable avatar",
      "image": ["/images/chat 1.png", "/images/chat 2.png","/images/chat 3.png","/images/chat 4.png","/images/chat 5.png"],
      "slug": "Snappy",
      "deploy": "",
      "frontend": "https://github.com/rahul12km/ChatApp",
      "backend": "https://github.com/rahul12km/ChatApp",
      "techUsed": "MERN stack | Styled Component | Rest API | Socket io "
    }
  ]
}
